{
  "id": "ibiyandike_mu_kifuliiru",
  "slug": "ibiyandike_mu_kifuliiru",
  "title": "Ibiyandike mu Kifuliiru",
  "contentType": "article",
  "data": {
    "type": "article",
    "title": "Ibiyandike mu Kifuliiru",
    "blocks": [
      {
        "type": "heading",
        "level": 1,
        "content": "Ibiyandike mu Kifuliiru"
      },
      {
        "type": "paragraph",
        "content": "Loonga ibindu byooshi ibiyandike mu Kifuliiru. Bino byangaba bitaabo, namuyehuulo kandi li ngisi kindi kyooshi umundu angaloonga ikiyandike mu Kifuliiru."
      }
    ]
  },
  "metadata": {
    "createdAt": "2025-12-08T22:02:08.604Z",
    "updatedAt": "2025-12-08T22:02:08.604Z",
    "tags": []
  }
}